umpyutl/__about__.py
umpyutl/__init__.py
umpyutl/convert.py
umpyutl/http.py
umpyutl/py.typed
umpyutl/read.py
umpyutl/write.py
umpyutl-2.1.1.dist-info/METADATA
umpyutl-2.1.1.dist-info/WHEEL
umpyutl-2.1.1.dist-info/licenses/LICENSE
umpyutl-2.1.1.dist-info/RECORD
