Metadata-Version: 2.3
Name: umpyutl
Version: 2.1.1
Summary: Utility classes and functions.
Project-URL: Homepage, https://github.com/umsi-arwhyte/umpyutl
Author-email: Anthony Whyte <anthwhyte@gmail.com>
License: BSD-3-Clause
License-File: LICENSE
Keywords: arwhyte,umpyutl,utilities
Classifier: License :: OSI Approved :: BSD License
Classifier: Operating System :: OS Independent
Classifier: Programming Language :: Python :: 3
Requires-Python: >=3.10
Requires-Dist: pyyaml
Requires-Dist: requests
